seed_vault/__init__.py
seed_vault/cli/__init__.py
seed_vault/cli/cli.py
seed_vault/enums/__init__.py
seed_vault/enums/common.py
seed_vault/enums/config.py
seed_vault/enums/ui.py
seed_vault/models/__init__.py
seed_vault/models/clients.csv
seed_vault/models/common.py
seed_vault/models/config.py
seed_vault/models/exception.py
seed_vault/models/url_mapping.py
seed_vault/service/__init__.py
seed_vault/service/config.cfg
seed_vault/service/config_direct.cfg
seed_vault/service/config_template.cfg
seed_vault/service/db.py
seed_vault/service/events.py
seed_vault/service/seismoloader.py
seed_vault/service/stations.py
seed_vault/service/utils.py
seed_vault/service/waveform.py
seed_vault/ui/__init__.py
seed_vault/ui/app.py
seed_vault/ui/app_pages/__init__.py
seed_vault/ui/app_pages/db_explorer.py
seed_vault/ui/app_pages/helpers/1_event_based.py
seed_vault/ui/app_pages/helpers/2_station_based.py
seed_vault/ui/app_pages/helpers/__init__.py
seed_vault/ui/app_pages/helpers/common.py
seed_vault/ui/app_pages/license.py
seed_vault/ui/app_pages/main_flows.py
seed_vault/ui/app_pages/run_from_parameters.py
seed_vault/ui/app_pages/settings.py
seed_vault/ui/components/base.py
seed_vault/ui/components/card.py
seed_vault/ui/components/continuous_waveform.py
seed_vault/ui/components/data_explorer.py
seed_vault/ui/components/display_log.py
seed_vault/ui/components/map.py
seed_vault/ui/components/run_from_config.py
seed_vault/ui/components/settings.py
seed_vault/ui/components/waveform.py
seed_vault/ui/components/workflows_combined.py
seed_vault/utils/__init__.py
seed_vault/utils/constants.py
seed_vault-1.1.0.dist-info/LICENSE
seed_vault-1.1.0.dist-info/METADATA
seed_vault-1.1.0.dist-info/WHEEL
seed_vault-1.1.0.dist-info/entry_points.txt
seed_vault-1.1.0.dist-info/RECORD
