Metadata-Version: 2.3
Name: seed-vault
Version: 1.1.0
Summary: GUI and CLI utility to interface with FDSN seismic data centers to search, download, and archive event and continuous waveform data.
Keywords: seismology,earthquakes,seismometers,FDSN,ObsPy,miniseed
Author: Robert Pickle
Author-email: robert.pickle@anu.edu.au
Requires-Python: >=3.10,<3.15
Classifier: Development Status :: 5 - Production/Stable
Classifier: Intended Audience :: Science/Research
Classifier: License :: OSI Approved
Classifier: Operating System :: POSIX :: Linux
Classifier: Operating System :: Microsoft :: Windows
Classifier: Operating System :: MacOS
Classifier: Programming Language :: Python :: 3
Classifier: Programming Language :: Python :: 3.10
Classifier: Programming Language :: Python :: 3.11
Classifier: Programming Language :: Python :: 3.12
Classifier: Programming Language :: Python :: 3.13
Classifier: Programming Language :: Python :: 3.14
Classifier: Topic :: Scientific/Engineering :: Physics
Requires-Dist: click (>=8.1.7,<9.0.0)
Requires-Dist: folium (>=0.20.0,<0.21.0)
Requires-Dist: matplotlib (>=3.8.5,<4.0.0)
Requires-Dist: obspy (>=1.4.2,<2.0.0)
Requires-Dist: pandas (>=2.2.2,<3.0.0)
Requires-Dist: pydantic (>=2.9.1,<3.0.0)
Requires-Dist: requests (>=2.32.3,<3.0.0)
Requires-Dist: st-pages (>=1.0.1,<2.0.0)
Requires-Dist: streamlit (>=1.52,<2.0)
Requires-Dist: streamlit-ace (>=0.1.1,<0.2.0)
Requires-Dist: streamlit-extras (>=0.6.0,<0.7.0)
Requires-Dist: streamlit-folium (==0.25.3)
Requires-Dist: tabulate (>=0.9.0,<0.10.0)
Requires-Dist: tqdm (>=4.67.1,<5.0.0)
